numba4jax/__init__.py
numba4jax/_version.py
numba4jax/_src/__init__.py
numba4jax/_src/c_api.py
numba4jax/_src/config_flags.py
numba4jax/_src/primitive_utils.py
numba4jax/_src/xla_utils.py
numba4jax/_src/backends/__init__.py
numba4jax/_src/backends/_cuda.py
numba4jax/_src/backends/_method_cache.py
numba4jax/_src/backends/cpu.py
numba4jax/_src/backends/gpu.py
numba4jax/_src/backends/utils.py
numba4jax-0.0.14.dist-info/METADATA
numba4jax-0.0.14.dist-info/WHEEL
numba4jax-0.0.14.dist-info/licenses/LICENSE.txt
numba4jax-0.0.14.dist-info/RECORD
