Metadata-Version: 2.3
Name: numba4jax
Version: 0.0.14
Summary: Usa numba in jax-compiled kernels.
Project-URL: homepage, http://github.com/PhilipVinc/numba4jax
Project-URL: repository, http://github.com/PhilipVinc/numba4jax
Author-email: Filippo Vicentini <filippovicentini@gmail.com>
License: MIT
License-File: LICENSE.txt
Keywords: Jax,Numba,compile,jit,kernel
Classifier: Development Status :: 5 - Production/Stable
Classifier: Intended Audience :: Science/Research
Classifier: Operating System :: MacOS :: MacOS X
Classifier: Operating System :: POSIX :: Linux
Classifier: Operating System :: Unix
Classifier: Programming Language :: Python :: 3
Requires-Python: >=3.10
Requires-Dist: cffi>=1.14.4
Requires-Dist: jax<0.5,>=0.4.31
Requires-Dist: numba<0.61,>=0.57
Requires-Dist: numpy<3.0,>=1.24
Provides-Extra: dev
Requires-Dist: black==24.8.0; extra == 'dev'
Requires-Dist: build; extra == 'dev'
Requires-Dist: coverage>=5; extra == 'dev'
Requires-Dist: flaky>=3.7; extra == 'dev'
Requires-Dist: pre-commit; extra == 'dev'
Requires-Dist: pytest-cov>=2.10.1; extra == 'dev'
Requires-Dist: pytest>=6; extra == 'dev'
Requires-Dist: ruff==0.5.6; extra == 'dev'
Requires-Dist: wheel; extra == 'dev'
